gitai/__init__.py
gitai/changelog.py
gitai/cli.py
gitai/commit.py
gitai/config.py
gitai/constants.py
gitai/diff.py
gitai/hook.py
gitai/util.py
gitai/providers/__init__.py
gitai/providers/base.py
gitai/providers/ollama_provider.py
gitai/providers/openai_provider.py
enhanced_git-1.0.7.dist-info/METADATA
enhanced_git-1.0.7.dist-info/WHEEL
enhanced_git-1.0.7.dist-info/entry_points.txt
enhanced_git-1.0.7.dist-info/licenses/LICENSE
enhanced_git-1.0.7.dist-info/RECORD
