Metadata-Version: 2.4
Name: enhanced-git
Version: 1.0.7
Summary: Generate Conventional Commit messages and changelog sections using AI
Project-URL: Homepage, https://github.com/mxzahid/git-ai
Project-URL: Repository, https://github.com/mxzahid/git-ai
Project-URL: Issues, https://github.com/mxzahid/git-ai/issues
Project-URL: Documentation, https://github.com/mxzahid/git-ai#readme
Author-email: Abdullah Zahid <abdullahzahid229@gmail.com>
Maintainer-email: Abdullah Zahid <abdullahzahid229@gmail.com>
License: MIT
License-File: LICENSE
Keywords: ai,changelog,commit,conventional-commits,git,llm
Classifier: Development Status :: 4 - Beta
Classifier: Intended Audience :: Developers
Classifier: License :: OSI Approved :: MIT License
Classifier: Operating System :: OS Independent
Classifier: Programming Language :: Python :: 3
Classifier: Programming Language :: Python :: 3.11
Classifier: Programming Language :: Python :: 3.12
Classifier: Topic :: Software Development :: Version Control :: Git
Classifier: Topic :: Utilities
Requires-Python: >=3.11
Requires-Dist: gitpython>=3.1.0
Requires-Dist: openai>=1.0.0
Requires-Dist: requests>=2.31.0
Requires-Dist: rich>=13.0.0
Requires-Dist: tomli>=2.0.0; python_version < '3.11'
Requires-Dist: typer>=0.9.0
Provides-Extra: dev
Requires-Dist: black>=23.0.0; extra == 'dev'
Requires-Dist: mypy>=1.0.0; extra == 'dev'
Requires-Dist: pre-commit>=3.0.0; extra == 'dev'
Requires-Dist: pytest-cov>=4.0.0; extra == 'dev'
Requires-Dist: pytest>=7.0.0; extra == 'dev'
Requires-Dist: types-requests>=2.31.0; extra == 'dev'
Provides-Extra: docs
Requires-Dist: mkdocs-material>=9.0.0; extra == 'docs'
Requires-Dist: mkdocs>=1.5.0; extra == 'docs'
